README.md
setup.py
suremco/__init__.py
suremco/__main__.py
suremco/_tracker.dll
suremco/_tracker.so
suremco/app.py
suremco/io.py
suremco/libwinpthread-1.dll
suremco/misc.py
suremco/nanoflann.hpp
suremco/tracker.cpp
suremco/tracker.py
suremco/tracker_test.py
suremco.egg-info/PKG-INFO
suremco.egg-info/SOURCES.txt
suremco.egg-info/dependency_links.txt
suremco.egg-info/requires.txt
suremco.egg-info/top_level.txt